covid19it/__init__.py
covid19it/covid19.py
covid19it-1.2.0.dist-info/METADATA
covid19it-1.2.0.dist-info/WHEEL
covid19it-1.2.0.dist-info/top_level.txt
covid19it-1.2.0.dist-info/RECORD
