Metadata-Version: 2.1
Name: covid19it
Version: 1.2.0
Summary: Covid-19 italy report
Home-page: https://github.com/mik3sw/Covid-19-Italy
Author: Mik3sw
License: MIT
Platform: UNKNOWN
Requires-Dist: requests
